feedbackloop/.DS_Store
feedbackloop/__init__.py
feedbackloop/handler.py
feedbackloop/handler_s3.py
feedbackloop/handler_sm.py
feedbackloop/request_processor.py
feedbackloop/request_processor_s3.py
feedbackloop/request_processor_sm.py
feedbackloop/simple_handler.py
feedbackloop/simple_request_processor.py
feedbackloop/DeepGreenFeedbackConnectorLambda/__init__.py
feedbackloop/DeepGreenFeedbackConnectorLambda/handler.py
feedbackloop/DeepGreenFeedbackConnectorLambda/request_processor.py
feedbackloop/DeepGreenFeedbackConnectorLambda/simple_handler.py
feedbackloop/DeepGreenFeedbackConnectorLambda/simple_request_processor.py
feedbackloop/DeepGreenFeedbackConnectorLambda/model/__init__.py
feedbackloop/DeepGreenFeedbackConnectorLambda/model/config_id.py
feedbackloop/DeepGreenFeedbackConnectorLambda/model/connector_config.py
feedbackloop/DeepGreenFeedbackConnectorLambda/model/feedback_config.py
feedbackloop/DeepGreenFeedbackConnectorLambda/model/feedback_input.py
feedbackloop/DeepGreenFeedbackConnectorLambda/model/filename.py
feedbackloop/DeepGreenFeedbackConnectorLambda/model/s3_key.py
feedbackloop/DeepGreenFeedbackConnectorLambda/model/s3_location.py
feedbackloop/DeepGreenFeedbackConnectorLambda/sampling/__init__.py
feedbackloop/DeepGreenFeedbackConnectorLambda/sampling/sampling_strategy.py
feedbackloop/DeepGreenFeedbackConnectorLambda/service/__init__.py
feedbackloop/DeepGreenFeedbackConnectorLambda/service/cloudwatch_metrics_publisher.py
feedbackloop/DeepGreenFeedbackConnectorLambda/service/model_input_uploader.py
feedbackloop/DeepGreenFeedbackConnectorLambda/service/model_input_uploader_nocw.py
feedbackloop/DeepGreenFeedbackConnectorLambda/service/model_prediction_publisher.py
feedbackloop/DeepGreenFeedbackConnectorLambda/service/status_publisher.py
feedbackloop/model/__init__.py
feedbackloop/model/component_config.py
feedbackloop/model/config_id.py
feedbackloop/model/connector_config.py
feedbackloop/model/feedback_config.py
feedbackloop/model/feedback_input.py
feedbackloop-1.0.2.dist-info/METADATA
feedbackloop-1.0.2.dist-info/WHEEL
feedbackloop-1.0.2.dist-info/top_level.txt
feedbackloop-1.0.2.dist-info/RECORD
