Metadata-Version: 2.1
Name: feedbackloop
Version: 1.0.2
Summary: feedback loop greengrass ML component
Home-page: UNKNOWN
Author: William Xi
Author-email: williaxi@amazon.com
License: UNKNOWN
Keywords: python,iot,aws,machine learning
Platform: UNKNOWN
Classifier: Development Status :: 1 - Planning
Classifier: Intended Audience :: Developers
Classifier: Programming Language :: Python :: 3
Classifier: Operating System :: Unix
Classifier: Operating System :: MacOS :: MacOS X
Classifier: Operating System :: Microsoft :: Windows
Requires-Dist: boto3
Requires-Dist: awsiotsdk
